wikipedia_downloader/__init__.py
wikipedia_downloader-0.2.dist-info/LICENSE
wikipedia_downloader-0.2.dist-info/METADATA
wikipedia_downloader-0.2.dist-info/WHEEL
wikipedia_downloader-0.2.dist-info/top_level.txt
wikipedia_downloader-0.2.dist-info/RECORD
