Metadata-Version: 2.1
Name: wikipedia-downloader
Version: 0.2
Summary: Download Wikipedia data dumps
Home-page: https://github.com/riccardobucco/wikipedia_downloader
Author: Riccardo Bucco
Author-email: riccardobucco@gmail.com
License: UNKNOWN
Keywords: wikipedia dump download
Platform: UNKNOWN
Classifier: Development Status :: 4 - Beta
Classifier: Programming Language :: Python :: 3
Classifier: License :: OSI Approved :: MIT License
Classifier: Operating System :: OS Independent
